JayTest/__init__.py
JayTest/print1.py
JayTest/print2.py
test/__init__.py
packjay_FXXKPYTHON-0.0.2.dist-info/LICENSE
packjay_FXXKPYTHON-0.0.2.dist-info/METADATA
packjay_FXXKPYTHON-0.0.2.dist-info/WHEEL
packjay_FXXKPYTHON-0.0.2.dist-info/top_level.txt
packjay_FXXKPYTHON-0.0.2.dist-info/RECORD
